{"type":"FeatureCollection","features":[{"type":"Feature","geometry":{"type":"Point","coordinates":[2.332384,48.880562]},"properties":{"#":1,"Score":0.97,"Qualité":"Numéro","Adresse géocodée":"5 Rue Paul Escudier 75009 Paris","adresse":"5 rue paul Escudier 75009 Paris","Code INSEE":"75109","Longitude":2.332384,"Latitude":48.880562}},{"type":"Feature","geometry":{"type":"Point","coordinates":[2.308628,48.85069899999999]},"properties":{"#":2,"Score":0.97,"Qualité":"Numéro","Adresse géocodée":"20 Avenue de Ségur 75007 Paris","adresse":"20 avenue de Ségur 75007 Paris","Code INSEE":"75107","Longitude":2.308628,"Latitude":48.850699}},{"type":"Feature","geometry":{"type":"Point","coordinates":[3.3199059999999996,48.97314800000001]},"properties":{"#":3,"Score":0.95,"Qualité":"Numéro","Adresse géocodée":"10 Rue des Chaumonts 02310 Saulchery","adresse":"10 rue des Chaumonts 02310 Saulchery","Code INSEE":"02701","Longitude":3.319906,"Latitude":48.973148}},{"type":"Feature","geometry":{"type":"Point","coordinates":[2.368761,48.846292999999974]},"properties":{"#":4,"Score":0.79,"Qualité":"Numéro","Adresse géocodée":"14 Avenue Ledru-Rollin 75012 Paris","adresse":"14 avenue Ledry Rollin 75012 Paris","Code INSEE":"75112","Longitude":2.368761,"Latitude":48.846293}}]}
